marops_config/__init__.py
marops_config/generate_schemas.py
marops_config/schemas/marops.schema.json
marops_config/test/marops_config_test.py
marops_config-3.9.0.dist-info/METADATA
marops_config-3.9.0.dist-info/WHEEL
marops_config-3.9.0.dist-info/top_level.txt
marops_config-3.9.0.dist-info/zip-safe
marops_config-3.9.0.dist-info/RECORD
