Metadata-Version: 2.1
Name: marops-config
Version: 3.9.0
Summary: A library for reading / writing MarOps config files
Home-page: https://github.com/Greenroom-Robotics/marops
Author: Greenroom Robotics
Author-email: team@greenroomrobotics.com
Maintainer: David Revay
Maintainer-email: david.revay@greenroomrobotics.com
License: Copyright (C) 2023, Greenroom Robotics
Keywords: colcon
Classifier: Development Status :: 3 - Alpha
Classifier: Environment :: Plugins
Classifier: Intended Audience :: Developers
Classifier: Programming Language :: Python
Classifier: Topic :: Software Development :: Build Tools
Requires-Dist: setuptools
Requires-Dist: dacite
Requires-Dist: PyYAML
Requires-Dist: dc-schema
